voicevox/__init__.py
voicevox/audio_query.py
voicevox/client.py
voicevox/errors.py
voicevox/http.py
voicevox/py.typed
voicevox/speaker_info.py
voicevox/speakers.py
voicevox/supported_devices.py
voicevox/types/__init__.py
voicevox/types/audio_query.py
voicevox/types/speaker_info.py
voicevox/types/speakers.py
voicevox_client-0.4.1.dist-info/LICENSE
voicevox_client-0.4.1.dist-info/METADATA
voicevox_client-0.4.1.dist-info/WHEEL
voicevox_client-0.4.1.dist-info/top_level.txt
voicevox_client-0.4.1.dist-info/RECORD
