Metadata-Version: 2.1
Name: voicevox-client
Version: 0.4.1
Summary: Voicevox engine unoffical wrapper
Home-page: https://github.com/voicevox-client/python
Author: tuna2134
License: MIT
Project-URL: Documentation, https://voicevox-client.tuna2134.jp
Project-URL: Source, https://github.com/voicevox-client/python
License-File: LICENSE
Requires-Dist: httpx>=0.23.2
Requires-Dist: typing-extensions>=4.3.0
Provides-Extra: tests
Requires-Dist: pytest; extra == "tests"
Requires-Dist: pytest-asyncio; extra == "tests"
Provides-Extra: docs
Requires-Dist: pdoc3; extra == "docs"
